sympl/__init__.py
sympl/_components/__init__.py
sympl/_components/basic.py
sympl/_components/netcdf.py
sympl/_components/plot.py
sympl/_components/timesteppers.py
sympl/_core/__init__.py
sympl/_core/base_components.py
sympl/_core/combine_properties.py
sympl/_core/composite.py
sympl/_core/constants.py
sympl/_core/dataarray.py
sympl/_core/exceptions.py
sympl/_core/get_np_arrays.py
sympl/_core/init_np_arrays.py
sympl/_core/restore_dataarray.py
sympl/_core/state.py
sympl/_core/tendencystepper.py
sympl/_core/time.py
sympl/_core/tracers.py
sympl/_core/units.py
sympl/_core/util.py
sympl/_core/wildcard.py
sympl/_core/wrappers.py
sympl-0.4.1.dist-info/AUTHORS.rst
sympl-0.4.1.dist-info/LICENSE
sympl-0.4.1.dist-info/METADATA
sympl-0.4.1.dist-info/WHEEL
sympl-0.4.1.dist-info/top_level.txt
sympl-0.4.1.dist-info/zip-safe
sympl-0.4.1.dist-info/RECORD
