Metadata-Version: 2.1
Name: sympl
Version: 0.4.1
Summary: Sympl is a Toolkit for building Earth system models in Python.
Home-page: https://github.com/mcgibbon/sympl
Author: Jeremy McGibbon
Author-email: mcgibbon@uw.edu
License: BSD license
Keywords: sympl
Classifier: Development Status :: 2 - Pre-Alpha
Classifier: Intended Audience :: Developers
Classifier: License :: OSI Approved :: BSD License
Classifier: Natural Language :: English
Classifier: Programming Language :: Python :: 2
Classifier: Programming Language :: Python :: 2.7
Classifier: Programming Language :: Python :: 3
Classifier: Programming Language :: Python :: 3.4
Classifier: Programming Language :: Python :: 3.5
License-File: LICENSE
License-File: AUTHORS.rst
Requires-Dist: numpy (>=1.12)
Requires-Dist: pint (>=0.7.0)
Requires-Dist: xarray (>=0.9.3)
Requires-Dist: six
